README
setup.py
django_subview.egg-info/PKG-INFO
django_subview.egg-info/SOURCES.txt
django_subview.egg-info/dependency_links.txt
django_subview.egg-info/top_level.txt
subview/__init__.py
subview/urls.py
subview/views.py
subview/templatetags/__init__.py
subview/templatetags/subview.py