Metadata-Version: 1.0
Name: django-subview
Version: 0.1.2
Summary: Treat Django views as reusable and generic components
Home-page: https://github.com/brstgt
Author: Benjamin Roth
Author-email: brstgt@gmail.com
License: UNKNOWN
Platform: any
Classifier: Development Status :: 1 - Planning
Classifier: Environment :: Web Environment
Classifier: Framework :: Django
Classifier: Intended Audience :: Developers
Classifier: Operating System :: OS Independent
Classifier: Programming Language :: Python
Classifier: Topic :: Software Development :: Libraries :: Application Frameworks
Classifier: Topic :: Software Development :: Libraries :: Python Modules
Classifier: License :: OSI Approved :: BSD License
